layercparse/__init__.py
layercparse/access.py
layercparse/cache.py
layercparse/codebase.py
layercparse/common.py
layercparse/ctoken.py
layercparse/function.py
layercparse/internal.py
layercparse/macro.py
layercparse/macroexpand.py
layercparse/record.py
layercparse/scan_sources_tool.py
layercparse/statement.py
layercparse/variable.py
layercparse/workspace.py
layercparse-0.4.3.dist-info/LICENSE
layercparse-0.4.3.dist-info/METADATA
layercparse-0.4.3.dist-info/WHEEL
layercparse-0.4.3.dist-info/top_level.txt
layercparse-0.4.3.dist-info/RECORD
