Metadata-Version: 2.1
Name: layercparse
Version: 0.4.3
Summary: Layered C parser
Home-page: https://github.com/ershov/layercparse
Author: Yury Ershov
License: GPL3
License-File: LICENSE
Requires-Dist: regex==2024.7.24
